[
    {
        "District": "Ri Bhoi",
        "IncreasingBlocks": [
            0,
            0,
            0,
            1,
            1,
            0,
            1,
            1,
            0,
            0,
            1,
            0,
            1,
            0,
            1,
            1,
            1,
            0,
            1,
            1,
            1,
            0,
            1,
            1,
            1,
            0,
            1,
            1,
            1,
            1,
            1,
            0,
            0,
            1,
            1,
            1,
            0,
            1,
            1,
            1,
            0,
            1,
            1,
            1,
            0,
            1,
            1,
            0,
            0,
            0,
            1,
            1,
            0,
            0,
            1,
            0,
            0,
            0,
            1,
            0,
            0,
            0,
            1,
            1,
            0,
            0,
            1,
            0,
            0,
            1,
            1,
            1,
            0,
            0,
            1,
            0,
            0,
            1,
            1,
            0,
            0,
            0,
            1,
            1,
            0,
            0,
            1,
            1,
            0,
            0,
            1,
            0
        ],
        "DecreasingBlocks": [
            1,
            1,
            1,
            0,
            0,
            1,
            0,
            0,
            1,
            1,
            0,
            1,
            0,
            1,
            0,
            0,
            0,
            1,
            0,
            0,
            0,
            1,
            0,
            0,
            0,
            1,
            0,
            0,
            0,
            0,
            0,
            1,
            1,
            0,
            0,
            0,
            1,
            0,
            0,
            0,
            1,
            0,
            0,
            0,
            1,
            0,
            0,
            1,
            1,
            1,
            0,
            0,
            1,
            1,
            0,
            1,
            1,
            1,
            0,
            1,
            1,
            1,
            0,
            0,
            1,
            1,
            0,
            1,
            1,
            0,
            0,
            0,
            1,
            1,
            0,
            1,
            1,
            0,
            0,
            1,
            1,
            1,
            0,
            0,
            1,
            1,
            0,
            0,
            1,
            1,
            0,
            1
        ],
        "CurrentLevel": [
            2.1,
            2.12,
            1.2,
            1.43,
            0.84,
            1.41,
            1.18,
            0.21,
            1.54,
            1.44,
            1.01,
            1.54,
            1.24,
            3.35,
            1.11,
            1.51,
            1.12,
            2.395,
            1.1,
            1.45,
            1.21,
            3.35,
            1.105,
            1.48,
            1.165,
            2.191818181818182,
            0.94,
            1.275,
            1.21,
            0.6,
            0.78,
            1.1,
            2.236666666666667,
            0.6,
            0.78,
            1.1,
            2.236666666666667,
            0.6,
            0.78,
            1.1,
            2.236666666666667,
            0.6,
            0.78,
            1.1,
            2.236666666666667,
            0.6,
            1.1477272727272727,
            1.8534615384615387,
            2.236666666666667,
            2.191818181818182,
            1.1477272727272727,
            1.8534615384615387,
            2.236666666666667,
            2.191818181818182,
            1.1477272727272727,
            1.91,
            3.28,
            2.191818181818182,
            1.1477272727272727,
            2.7175,
            3.6525,
            3.01,
            1.81,
            1.91,
            3.28,
            2.9175,
            1.5425,
            3.5250000000000004,
            4.025,
            3.01,
            1.81,
            2.205,
            2.475,
            2.825,
            1.275,
            2.65,
            2.71,
            1.11,
            0.98,
            1.82,
            3.0,
            2.845,
            1.16,
            2.30375,
            3.0033333333333334,
            2.85,
            1.02,
            1.96,
            3.3,
            2.55,
            1.09,
            2.785
        ],
        "AlgoLevel": [
            NaN,
            NaN,
            NaN,
            1.7125,
            1.3975,
            1.22,
            1.215,
            0.91,
            1.085,
            1.0924999999999998,
            1.0499999999999998,
            1.3824999999999998,
            1.3075,
            1.785,
            1.81,
            1.8025,
            1.7725,
            1.53375,
            1.5312499999999998,
            1.51625,
            1.5387499999999998,
            1.7775,
            1.77875,
            1.78625,
            1.775,
            1.4854545454545458,
            1.4442045454545456,
            1.3929545454545456,
            1.4042045454545455,
            1.00625,
            0.9662500000000002,
            0.9225000000000002,
            1.179166666666667,
            1.179166666666667,
            1.179166666666667,
            1.1791666666666671,
            1.1791666666666671,
            1.1791666666666671,
            1.1791666666666671,
            1.1791666666666671,
            1.1791666666666671,
            1.1791666666666671,
            1.1791666666666671,
            1.1791666666666671,
            1.1791666666666671,
            1.1791666666666671,
            1.2710984848484852,
            1.4594638694638695,
            1.4594638694638695,
            1.8574184149184152,
            1.8574184149184156,
            1.8574184149184156,
            1.857418414918416,
            1.857418414918416,
            1.857418414918416,
            1.871553030303031,
            2.1323863636363645,
            2.1323863636363645,
            2.1323863636363645,
            2.3342613636363643,
            2.4273863636363644,
            2.6319318181818185,
            2.7975000000000008,
            2.595625000000001,
            2.502500000000001,
            2.479375000000001,
            2.412500000000001,
            2.816250000000001,
            3.0025000000000013,
            3.025625000000001,
            3.092500000000001,
            2.762500000000001,
            2.375000000000001,
            2.3287500000000008,
            2.1950000000000007,
            2.306250000000001,
            2.3650000000000007,
            1.9362500000000005,
            1.8625000000000005,
            1.6550000000000002,
            1.7275000000000005,
            2.1612500000000003,
            2.2062500000000003,
            2.3271875,
            2.328020833333333,
            2.329270833333333,
            2.294270833333333,
            2.208333333333333,
            2.2825,
            2.2075,
            2.225,
            2.4312500000000004
        ],
        "blocks": [
            {
                "Block": "Nongpoh",
                "CurrentLevel": [
                    2.1,
                    2.12,
                    1.2,
                    1.43,
                    0.84,
                    1.41,
                    1.18,
                    0.21,
                    1.54,
                    1.44,
                    1.01,
                    1.54,
                    1.24,
                    3.35,
                    1.11,
                    1.51,
                    1.12,
                    2.395,
                    1.1,
                    1.45,
                    1.21,
                    3.35,
                    1.105,
                    1.48,
                    1.165,
                    2.191818181818182,
                    0.94,
                    1.275,
                    1.21,
                    0.6,
                    0.78,
                    1.1,
                    2.236666666666667,
                    0.6,
                    0.78,
                    1.1,
                    2.236666666666667,
                    0.6,
                    0.78,
                    1.1,
                    2.236666666666667,
                    0.6,
                    0.78,
                    1.1,
                    2.236666666666667,
                    0.6,
                    1.1477272727272727,
                    1.8534615384615387,
                    2.236666666666667,
                    2.191818181818182,
                    1.1477272727272727,
                    1.8534615384615387,
                    2.236666666666667,
                    2.191818181818182,
                    1.1477272727272727,
                    1.91,
                    3.28,
                    2.191818181818182,
                    1.1477272727272727,
                    2.7175,
                    3.6525,
                    3.01,
                    1.81,
                    1.91,
                    3.28,
                    2.9175,
                    1.5425,
                    3.5250000000000004,
                    4.025,
                    3.01,
                    1.81,
                    2.205,
                    2.475,
                    2.825,
                    1.275,
                    2.65,
                    2.71,
                    1.11,
                    0.98,
                    1.82,
                    3.0,
                    2.845,
                    1.16,
                    2.30375,
                    3.0033333333333334,
                    2.85,
                    1.02,
                    1.96,
                    3.3,
                    2.55,
                    1.09,
                    2.785
                ],
                "AlgoLevel": [
                    NaN,
                    NaN,
                    NaN,
                    1.7125,
                    1.3975,
                    1.22,
                    1.215,
                    0.91,
                    1.085,
                    1.0924999999999998,
                    1.0499999999999998,
                    1.3824999999999998,
                    1.3075,
                    1.785,
                    1.81,
                    1.8025,
                    1.7725,
                    1.53375,
                    1.5312499999999998,
                    1.51625,
                    1.5387499999999998,
                    1.7775,
                    1.77875,
                    1.78625,
                    1.775,
                    1.4854545454545458,
                    1.4442045454545456,
                    1.3929545454545456,
                    1.4042045454545455,
                    1.00625,
                    0.9662500000000002,
                    0.9225000000000002,
                    1.179166666666667,
                    1.179166666666667,
                    1.179166666666667,
                    1.1791666666666671,
                    1.1791666666666671,
                    1.1791666666666671,
                    1.1791666666666671,
                    1.1791666666666671,
                    1.1791666666666671,
                    1.1791666666666671,
                    1.1791666666666671,
                    1.1791666666666671,
                    1.1791666666666671,
                    1.1791666666666671,
                    1.2710984848484852,
                    1.4594638694638695,
                    1.4594638694638695,
                    1.8574184149184152,
                    1.8574184149184156,
                    1.8574184149184156,
                    1.857418414918416,
                    1.857418414918416,
                    1.857418414918416,
                    1.871553030303031,
                    2.1323863636363645,
                    2.1323863636363645,
                    2.1323863636363645,
                    2.3342613636363643,
                    2.4273863636363644,
                    2.6319318181818185,
                    2.7975000000000008,
                    2.595625000000001,
                    2.502500000000001,
                    2.479375000000001,
                    2.412500000000001,
                    2.816250000000001,
                    3.0025000000000013,
                    3.025625000000001,
                    3.092500000000001,
                    2.762500000000001,
                    2.375000000000001,
                    2.3287500000000008,
                    2.1950000000000007,
                    2.306250000000001,
                    2.3650000000000007,
                    1.9362500000000005,
                    1.8625000000000005,
                    1.6550000000000002,
                    1.7275000000000005,
                    2.1612500000000003,
                    2.2062500000000003,
                    2.3271875,
                    2.328020833333333,
                    2.329270833333333,
                    2.294270833333333,
                    2.208333333333333,
                    2.2825,
                    2.2075,
                    2.225,
                    2.4312500000000004
                ]
            }
        ]
    },
    {
        "District": "East Khasi Hills",
        "IncreasingBlocks": [
            0,
            0,
            0,
            1,
            0,
            0,
            1,
            1,
            0,
            0,
            1,
            1,
            1,
            0,
            1,
            1,
            0,
            0,
            1,
            1,
            0,
            0,
            1,
            1,
            0,
            1,
            1,
            0,
            0,
            1,
            1,
            0,
            1,
            0,
            1,
            0,
            0,
            1,
            1,
            1,
            0,
            0,
            1,
            0,
            0,
            1,
            1,
            1,
            0,
            0,
            1,
            1,
            0,
            1,
            1,
            1,
            0,
            0,
            1,
            1,
            0,
            1,
            1,
            1,
            0,
            0,
            1,
            1,
            1,
            0,
            1,
            1,
            1,
            0,
            1,
            1,
            1,
            1,
            0,
            0,
            0,
            1,
            1,
            1,
            0,
            1,
            0,
            0,
            1,
            0,
            1,
            1
        ],
        "DecreasingBlocks": [
            1,
            1,
            1,
            0,
            1,
            1,
            0,
            0,
            1,
            1,
            0,
            0,
            0,
            1,
            0,
            0,
            1,
            1,
            0,
            0,
            1,
            1,
            0,
            0,
            1,
            0,
            0,
            1,
            1,
            0,
            0,
            1,
            0,
            1,
            0,
            1,
            1,
            0,
            0,
            0,
            1,
            1,
            0,
            1,
            1,
            0,
            0,
            0,
            1,
            1,
            0,
            0,
            1,
            0,
            0,
            0,
            1,
            1,
            0,
            0,
            1,
            0,
            0,
            0,
            1,
            1,
            0,
            0,
            0,
            1,
            0,
            0,
            0,
            1,
            0,
            0,
            0,
            0,
            1,
            1,
            1,
            0,
            0,
            0,
            1,
            0,
            1,
            1,
            0,
            1,
            0,
            0
        ],
        "CurrentLevel": [
            2.7675,
            1.7559999999999998,
            1.034,
            1.528,
            2.032,
            2.52,
            1.1825,
            1.194,
            1.81,
            1.9825,
            1.045,
            1.232,
            1.3779999999999997,
            2.2175,
            1.0825,
            1.4820000000000002,
            2.064,
            2.555,
            1.15,
            0.6975,
            1.7439999999999998,
            2.036,
            0.902,
            1.4499999999999995,
            2.15,
            1.2260000000000002,
            1.118,
            1.608,
            2.728,
            1.8119999999999998,
            0.9559999999999998,
            2.1575,
            1.5750000000000002,
            1.835,
            0.955,
            2.6133333333333333,
            2.325,
            1.89,
            2.273333333333333,
            1.5025,
            1.9325,
            3.24,
            1.6033333333333333,
            25.065,
            21.0,
            1.8575,
            1.356666666666667,
            1.4925000000000002,
            2.945,
            2.54875,
            1.36,
            2.016666666666667,
            3.1725,
            1.8575,
            1.1133333333333333,
            1.62,
            3.305,
            2.212239583333333,
            1.24,
            1.8225,
            4.13,
            2.212239583333333,
            1.346666666666667,
            1.7374999999999998,
            3.615,
            4.963333333333334,
            1.4941666666666666,
            2.34,
            2.8266666666666667,
            3.459166666666667,
            1.345,
            1.885,
            1.6233333333333333,
            4.963333333333334,
            2.045,
            2.26875,
            2.978333333333333,
            1.955,
            2.82,
            2.9,
            4.485,
            2.617083333333333,
            1.88,
            1.95,
            2.5675000000000003,
            0.15,
            1.65,
            1.9283333333333328,
            0.65,
            3.4,
            1.765,
            0.935
        ],
        "AlgoLevel": [
            NaN,
            NaN,
            NaN,
            1.771375,
            1.5875,
            1.7784999999999995,
            1.815625,
            1.7321249999999997,
            1.6766249999999996,
            1.5422499999999997,
            1.5078749999999996,
            1.5173749999999997,
            1.4093749999999994,
            1.4681249999999992,
            1.4774999999999991,
            1.5399999999999991,
            1.7114999999999991,
            1.7958749999999992,
            1.8127499999999996,
            1.616624999999999,
            1.536624999999999,
            1.4068749999999992,
            1.3448749999999992,
            1.532999999999999,
            1.6344999999999992,
            1.431999999999999,
            1.485999999999999,
            1.5254999999999992,
            1.669999999999999,
            1.8164999999999991,
            1.7759999999999991,
            1.9133749999999992,
            1.6251249999999993,
            1.6308749999999992,
            1.630624999999999,
            1.7445833333333325,
            1.9320833333333327,
            1.9458333333333329,
            2.2754166666666658,
            1.9977083333333323,
            1.8995833333333316,
            2.237083333333332,
            2.069583333333332,
            7.960208333333331,
            12.727083333333333,
            12.381458333333333,
            12.319791666666665,
            6.426666666666665,
            1.912916666666665,
            2.085729166666665,
            2.086562499999998,
            2.217604166666665,
            2.2744791666666653,
            2.1016666666666652,
            2.0399999999999983,
            1.940833333333332,
            1.973958333333332,
            2.062643229166665,
            2.0943098958333315,
            2.1449348958333316,
            2.351184895833332,
            2.351184895833332,
            2.3778515624999987,
            2.3566015624999985,
            2.2278515624999993,
            2.9156249999999995,
            2.9524999999999992,
            3.1031249999999995,
            2.9060416666666664,
            2.53,
            2.4927083333333333,
            2.3789583333333333,
            2.078125,
            2.454166666666666,
            2.629166666666666,
            2.7251041666666658,
            3.0638541666666663,
            2.3117708333333318,
            2.5055208333333323,
            2.6633333333333318,
            3.0399999999999987,
            3.205520833333332,
            2.970520833333332,
            2.7330208333333315,
            2.253645833333332,
            1.6368749999999983,
            1.5793749999999986,
            1.5739583333333316,
            1.094583333333332,
            1.907083333333332,
            1.935833333333332,
            1.6874999999999991
        ],
        "blocks": [
            {
                "Block": "Mawkynrew",
                "CurrentLevel": [
                    2.7675,
                    1.7559999999999998,
                    1.034,
                    1.528,
                    2.032,
                    2.52,
                    1.1825,
                    1.194,
                    1.81,
                    1.9825,
                    1.045,
                    1.232,
                    1.3779999999999997,
                    2.2175,
                    1.0825,
                    1.4820000000000002,
                    2.064,
                    2.555,
                    1.15,
                    0.6975,
                    1.7439999999999998,
                    2.036,
                    0.902,
                    1.4499999999999995,
                    2.15,
                    1.2260000000000002,
                    1.118,
                    1.608,
                    2.728,
                    1.8119999999999998,
                    0.9559999999999998,
                    2.1575,
                    1.5750000000000002,
                    1.835,
                    0.955,
                    2.6133333333333333,
                    2.325,
                    1.89,
                    2.273333333333333,
                    1.5025,
                    1.9325,
                    3.24,
                    1.6033333333333333,
                    25.065,
                    21.0,
                    1.8575,
                    1.356666666666667,
                    1.4925000000000002,
                    2.945,
                    2.54875,
                    1.36,
                    2.016666666666667,
                    3.1725,
                    1.8575,
                    1.1133333333333333,
                    1.62,
                    3.305,
                    2.212239583333333,
                    1.24,
                    1.8225,
                    4.13,
                    2.212239583333333,
                    1.346666666666667,
                    1.7374999999999998,
                    3.615,
                    4.963333333333334,
                    1.4941666666666666,
                    2.34,
                    2.8266666666666667,
                    3.459166666666667,
                    1.345,
                    1.885,
                    1.6233333333333333,
                    4.963333333333334,
                    2.045,
                    2.26875,
                    2.978333333333333,
                    1.955,
                    2.82,
                    2.9,
                    4.485,
                    2.617083333333333,
                    1.88,
                    1.95,
                    2.5675000000000003,
                    0.15,
                    1.65,
                    1.9283333333333328,
                    0.65,
                    3.4,
                    1.765,
                    0.935
                ],
                "AlgoLevel": [
                    NaN,
                    NaN,
                    NaN,
                    1.771375,
                    1.5875,
                    1.7784999999999995,
                    1.815625,
                    1.7321249999999997,
                    1.6766249999999996,
                    1.5422499999999997,
                    1.5078749999999996,
                    1.5173749999999997,
                    1.4093749999999994,
                    1.4681249999999992,
                    1.4774999999999991,
                    1.5399999999999991,
                    1.7114999999999991,
                    1.7958749999999992,
                    1.8127499999999996,
                    1.616624999999999,
                    1.536624999999999,
                    1.4068749999999992,
                    1.3448749999999992,
                    1.532999999999999,
                    1.6344999999999992,
                    1.431999999999999,
                    1.485999999999999,
                    1.5254999999999992,
                    1.669999999999999,
                    1.8164999999999991,
                    1.7759999999999991,
                    1.9133749999999992,
                    1.6251249999999993,
                    1.6308749999999992,
                    1.630624999999999,
                    1.7445833333333325,
                    1.9320833333333327,
                    1.9458333333333329,
                    2.2754166666666658,
                    1.9977083333333323,
                    1.8995833333333316,
                    2.237083333333332,
                    2.069583333333332,
                    7.960208333333331,
                    12.727083333333333,
                    12.381458333333333,
                    12.319791666666665,
                    6.426666666666665,
                    1.912916666666665,
                    2.085729166666665,
                    2.086562499999998,
                    2.217604166666665,
                    2.2744791666666653,
                    2.1016666666666652,
                    2.0399999999999983,
                    1.940833333333332,
                    1.973958333333332,
                    2.062643229166665,
                    2.0943098958333315,
                    2.1449348958333316,
                    2.351184895833332,
                    2.351184895833332,
                    2.3778515624999987,
                    2.3566015624999985,
                    2.2278515624999993,
                    2.9156249999999995,
                    2.9524999999999992,
                    3.1031249999999995,
                    2.9060416666666664,
                    2.53,
                    2.4927083333333333,
                    2.3789583333333333,
                    2.078125,
                    2.454166666666666,
                    2.629166666666666,
                    2.7251041666666658,
                    3.0638541666666663,
                    2.3117708333333318,
                    2.5055208333333323,
                    2.6633333333333318,
                    3.0399999999999987,
                    3.205520833333332,
                    2.970520833333332,
                    2.7330208333333315,
                    2.253645833333332,
                    1.6368749999999983,
                    1.5793749999999986,
                    1.5739583333333316,
                    1.094583333333332,
                    1.907083333333332,
                    1.935833333333332,
                    1.6874999999999991
                ]
            }
        ]
    },
    {
        "District": "South Garo Hills",
        "IncreasingBlocks": [
            0,
            0,
            0,
            1,
            0,
            0,
            1,
            1,
            0,
            0,
            1,
            1,
            0,
            0,
            1,
            1,
            0,
            1,
            1,
            1,
            0,
            0,
            1,
            1,
            1,
            1,
            1,
            0,
            0,
            0,
            1,
            1,
            1,
            0,
            0,
            0,
            1,
            0,
            1,
            0,
            0,
            0,
            1,
            1,
            1,
            1,
            0,
            0,
            0,
            1,
            1,
            0,
            0,
            1,
            1,
            0,
            0,
            0,
            1,
            1,
            0,
            0,
            1,
            1,
            0,
            0,
            1,
            1,
            0,
            0,
            1,
            1,
            0,
            0,
            1,
            1,
            0,
            0,
            1,
            1,
            0,
            0,
            1,
            1,
            0,
            0,
            1,
            1,
            1,
            0,
            1,
            1
        ],
        "DecreasingBlocks": [
            1,
            1,
            1,
            0,
            1,
            1,
            0,
            0,
            1,
            1,
            0,
            0,
            1,
            1,
            0,
            0,
            1,
            0,
            0,
            0,
            1,
            1,
            0,
            0,
            0,
            0,
            0,
            1,
            1,
            1,
            0,
            0,
            0,
            1,
            1,
            1,
            0,
            1,
            0,
            1,
            1,
            1,
            0,
            0,
            0,
            0,
            1,
            1,
            1,
            0,
            0,
            1,
            1,
            0,
            0,
            1,
            1,
            1,
            0,
            0,
            1,
            1,
            0,
            0,
            1,
            1,
            0,
            0,
            1,
            1,
            0,
            0,
            1,
            1,
            0,
            0,
            1,
            1,
            0,
            0,
            1,
            1,
            0,
            0,
            1,
            1,
            0,
            0,
            0,
            1,
            0,
            0
        ],
        "CurrentLevel": [
            5.035,
            5.72,
            3.88,
            4.18,
            4.87,
            5.2799999999999985,
            2.875,
            3.57,
            4.5,
            5.03,
            3.95,
            4.425000000000002,
            4.8599999999999985,
            5.2,
            3.45,
            4.1,
            6.085,
            4.14,
            4.16,
            4.73,
            5.26,
            5.87,
            2.785,
            3.83125,
            3.96,
            2.855,
            2.395,
            3.205,
            3.715,
            4.35,
            2.79,
            3.29,
            2.495,
            4.745,
            3.8,
            4.51,
            3.97,
            4.34,
            3.89,
            4.39,
            5.39,
            5.11,
            4.6,
            3.54,
            3.875,
            2.65,
            4.1175000000000015,
            4.67,
            5.52,
            3.88,
            4.61,
            4.6850000000000005,
            5.295,
            2.65,
            3.37,
            4.71,
            5.505000000000001,
            4.8406666666666665,
            4.28,
            4.03,
            4.83,
            4.97,
            4.03,
            3.89,
            4.75,
            5.0,
            4.046666666666667,
            4.12,
            4.65,
            4.97,
            3.83,
            4.005,
            5.513333333333333,
            5.03,
            3.78,
            4.12,
            7.14,
            7.32,
            3.73,
            4.1278125,
            7.14,
            6.1750000000000025,
            3.73,
            4.1278125,
            7.14,
            7.32,
            3.73,
            4.1278125,
            4.826578947368421,
            4.8406666666666665,
            3.672058823529412,
            4.1278125
        ],
        "AlgoLevel": [
            NaN,
            NaN,
            NaN,
            4.7037499999999985,
            4.6625,
            4.5525,
            4.3012500000000005,
            4.1487500000000015,
            4.05625,
            3.9937500000000012,
            4.262500000000001,
            4.476250000000001,
            4.566250000000001,
            4.6087500000000015,
            4.4837500000000015,
            4.402500000000002,
            4.708750000000001,
            4.443750000000001,
            4.621250000000002,
            4.778750000000001,
            4.572500000000002,
            5.005000000000002,
            4.661250000000002,
            4.436562500000002,
            4.111562500000002,
            3.3578125000000014,
            3.2603125000000013,
            3.1037500000000007,
            3.0425000000000004,
            3.4162500000000007,
            3.515000000000001,
            3.5362500000000003,
            3.23125,
            3.3300000000000005,
            3.5825000000000005,
            3.887500000000001,
            4.2562500000000005,
            4.155,
            4.1775,
            4.147500000000001,
            4.502500000000001,
            4.695000000000001,
            4.8725000000000005,
            4.66,
            4.28125,
            3.66625,
            3.545625,
            3.828125,
            4.239375,
            4.546875,
            4.67,
            4.67375,
            4.6175000000000015,
            4.3100000000000005,
            4.000000000000001,
            4.006250000000001,
            4.058750000000002,
            4.606416666666669,
            4.833916666666669,
            4.663916666666669,
            4.495166666666668,
            4.527500000000002,
            4.465000000000002,
            4.4300000000000015,
            4.41,
            4.4175,
            4.421666666666667,
            4.479166666666667,
            4.454166666666668,
            4.446666666666667,
            4.3925,
            4.36375,
            4.579583333333332,
            4.5945833333333335,
            4.582083333333333,
            4.610833333333334,
            5.017500000000001,
            5.590000000000002,
            5.5775000000000015,
            5.5794531250000015,
            5.5794531250000015,
            5.293203125000002,
            5.293203125000002,
            5.293203125000002,
            5.293203125000002,
            5.5794531250000015,
            5.5794531250000015,
            5.5794531250000015,
            5.001097861842107,
            4.381264528508773,
            4.3667792343911245,
            4.3667792343911245
        ],
        "blocks": [
            {
                "Block": "Baghmara",
                "CurrentLevel": [
                    5.035,
                    5.72,
                    3.88,
                    4.18,
                    4.87,
                    5.2799999999999985,
                    2.875,
                    3.57,
                    4.5,
                    5.03,
                    3.95,
                    4.425000000000002,
                    4.8599999999999985,
                    5.2,
                    3.45,
                    4.1,
                    6.085,
                    4.14,
                    4.16,
                    4.73,
                    5.26,
                    5.87,
                    2.785,
                    3.83125,
                    3.96,
                    2.855,
                    2.395,
                    3.205,
                    3.715,
                    4.35,
                    2.79,
                    3.29,
                    2.495,
                    4.745,
                    3.8,
                    4.51,
                    3.97,
                    4.34,
                    3.89,
                    4.39,
                    5.39,
                    5.11,
                    4.6,
                    3.54,
                    3.875,
                    2.65,
                    4.1175000000000015,
                    4.67,
                    5.52,
                    3.88,
                    4.61,
                    4.6850000000000005,
                    5.295,
                    2.65,
                    3.37,
                    4.71,
                    5.505000000000001,
                    4.8406666666666665,
                    4.28,
                    4.03,
                    4.83,
                    4.97,
                    4.03,
                    3.89,
                    4.75,
                    5.0,
                    4.046666666666667,
                    4.12,
                    4.65,
                    4.97,
                    3.83,
                    4.005,
                    5.513333333333333,
                    5.03,
                    3.78,
                    4.12,
                    7.14,
                    7.32,
                    3.73,
                    4.1278125,
                    7.14,
                    6.1750000000000025,
                    3.73,
                    4.1278125,
                    7.14,
                    7.32,
                    3.73,
                    4.1278125,
                    4.826578947368421,
                    4.8406666666666665,
                    3.672058823529412,
                    4.1278125
                ],
                "AlgoLevel": [
                    NaN,
                    NaN,
                    NaN,
                    4.7037499999999985,
                    4.6625,
                    4.5525,
                    4.3012500000000005,
                    4.1487500000000015,
                    4.05625,
                    3.9937500000000012,
                    4.262500000000001,
                    4.476250000000001,
                    4.566250000000001,
                    4.6087500000000015,
                    4.4837500000000015,
                    4.402500000000002,
                    4.708750000000001,
                    4.443750000000001,
                    4.621250000000002,
                    4.778750000000001,
                    4.572500000000002,
                    5.005000000000002,
                    4.661250000000002,
                    4.436562500000002,
                    4.111562500000002,
                    3.3578125000000014,
                    3.2603125000000013,
                    3.1037500000000007,
                    3.0425000000000004,
                    3.4162500000000007,
                    3.515000000000001,
                    3.5362500000000003,
                    3.23125,
                    3.3300000000000005,
                    3.5825000000000005,
                    3.887500000000001,
                    4.2562500000000005,
                    4.155,
                    4.1775,
                    4.147500000000001,
                    4.502500000000001,
                    4.695000000000001,
                    4.8725000000000005,
                    4.66,
                    4.28125,
                    3.66625,
                    3.545625,
                    3.828125,
                    4.239375,
                    4.546875,
                    4.67,
                    4.67375,
                    4.6175000000000015,
                    4.3100000000000005,
                    4.000000000000001,
                    4.006250000000001,
                    4.058750000000002,
                    4.606416666666669,
                    4.833916666666669,
                    4.663916666666669,
                    4.495166666666668,
                    4.527500000000002,
                    4.465000000000002,
                    4.4300000000000015,
                    4.41,
                    4.4175,
                    4.421666666666667,
                    4.479166666666667,
                    4.454166666666668,
                    4.446666666666667,
                    4.3925,
                    4.36375,
                    4.579583333333332,
                    4.5945833333333335,
                    4.582083333333333,
                    4.610833333333334,
                    5.017500000000001,
                    5.590000000000002,
                    5.5775000000000015,
                    5.5794531250000015,
                    5.5794531250000015,
                    5.293203125000002,
                    5.293203125000002,
                    5.293203125000002,
                    5.293203125000002,
                    5.5794531250000015,
                    5.5794531250000015,
                    5.5794531250000015,
                    5.001097861842107,
                    4.381264528508773,
                    4.3667792343911245,
                    4.3667792343911245
                ]
            }
        ]
    },
    {
        "District": "West Garo Hills",
        "IncreasingBlocks": [
            0,
            0,
            0,
            1,
            0,
            0,
            1,
            1,
            0,
            0,
            1,
            1,
            0,
            0,
            1,
            0,
            0,
            0,
            1,
            1,
            0,
            0,
            1,
            1,
            0,
            1,
            1,
            0,
            0,
            0,
            1,
            0,
            0,
            0,
            1,
            1,
            0,
            1,
            1,
            1,
            0,
            0,
            1,
            1,
            0,
            0,
            0,
            1,
            0,
            1,
            1,
            1,
            0,
            1,
            1,
            1,
            0,
            0,
            1,
            1,
            0,
            0,
            1,
            1,
            0,
            0,
            1,
            1,
            0,
            0,
            1,
            1,
            0,
            0,
            1,
            1,
            0,
            0,
            0,
            1,
            1,
            1,
            1,
            1,
            0,
            0,
            1,
            1,
            0,
            0,
            1,
            1
        ],
        "DecreasingBlocks": [
            1,
            1,
            1,
            0,
            1,
            1,
            0,
            0,
            1,
            1,
            0,
            0,
            1,
            1,
            0,
            1,
            1,
            1,
            0,
            0,
            1,
            1,
            0,
            0,
            1,
            0,
            0,
            1,
            1,
            1,
            0,
            1,
            1,
            1,
            0,
            0,
            1,
            0,
            0,
            0,
            1,
            1,
            0,
            0,
            1,
            1,
            1,
            0,
            1,
            0,
            0,
            0,
            1,
            0,
            0,
            0,
            1,
            1,
            0,
            0,
            1,
            1,
            0,
            0,
            1,
            1,
            0,
            0,
            1,
            1,
            0,
            0,
            1,
            1,
            0,
            0,
            1,
            1,
            1,
            0,
            0,
            0,
            0,
            0,
            1,
            1,
            0,
            0,
            1,
            1,
            0,
            0
        ],
        "CurrentLevel": [
            3.1060000000000003,
            3.1049999999999995,
            1.7785714285714287,
            1.85625,
            2.29,
            3.1825,
            1.912727272727273,
            2.24,
            2.77,
            2.78625,
            1.5683333333333334,
            2.0645454545454545,
            2.2945454545454544,
            3.255,
            0.7799999999999999,
            2.225555555555556,
            2.8966666666666665,
            3.12625,
            1.4144444444444444,
            1.98625,
            2.87125,
            3.4044444444444446,
            1.742222222222222,
            2.091666666666667,
            2.806666666666666,
            2.03111111111111,
            1.6688888888888893,
            2.263,
            2.645454545454545,
            2.74,
            2.1881818181818184,
            2.5922222222222224,
            2.628888888888889,
            3.25375,
            1.88,
            2.4214285714285717,
            3.2755555555555564,
            1.79875,
            1.3924999999999998,
            1.5955555555555554,
            2.6611111111111105,
            2.936666666666666,
            2.1425,
            2.213,
            2.5537499999999995,
            2.793333333333333,
            3.29,
            2.205555555555556,
            3.2110000000000007,
            2.865,
            2.6922222222222225,
            2.786666666666667,
            3.638888888888889,
            2.793333333333333,
            2.014545454545455,
            2.265555555555556,
            3.208,
            3.3388681657848327,
            2.451,
            2.4711111111111115,
            3.235555555555555,
            4.09,
            2.397,
            2.8877777777777784,
            3.9877777777777776,
            4.324285714285715,
            2.462666666666667,
            2.927272727272728,
            3.416363636363637,
            4.09,
            2.54,
            3.206127946127946,
            3.7572853535353534,
            4.558571428571429,
            3.0980000000000003,
            3.1910353535353533,
            3.7975,
            3.8819999999999997,
            4.15,
            3.803333333333333,
            3.8275,
            3.916,
            2.6039999999999996,
            2.8425,
            3.7191666666666654,
            4.18,
            2.4455555555555555,
            2.6275,
            3.5325,
            5.06,
            2.56,
            2.62
        ],
        "AlgoLevel": [
            NaN,
            NaN,
            NaN,
            2.461455357142857,
            2.2574553571428573,
            2.276830357142857,
            2.3103693181818183,
            2.4063068181818186,
            2.5263068181818182,
            2.4272443181818177,
            2.341145833333333,
            2.2972821969696966,
            2.1784185606060604,
            2.295606060606061,
            2.098522727272728,
            2.1387752525252526,
            2.2893055555555555,
            2.2571180555555563,
            2.415729166666668,
            2.3559027777777786,
            2.349548611111112,
            2.419097222222223,
            2.5010416666666675,
            2.527395833333334,
            2.511250000000001,
            2.167916666666668,
            2.149583333333334,
            2.192416666666668,
            2.152113636363637,
            2.3293358585858592,
            2.459159090909092,
            2.5414646464646475,
            2.5373232323232338,
            2.6657607323232337,
            2.5887152777777795,
            2.546016865079366,
            2.7076835317460333,
            2.343933531746033,
            2.222058531746033,
            2.0155902777777794,
            1.861979166666668,
            2.1464583333333342,
            2.3339583333333342,
            2.4883194444444454,
            2.461479166666668,
            2.4256458333333346,
            2.712520833333335,
            2.710659722222224,
            2.8749722222222243,
            2.8928888888888915,
            2.7434444444444464,
            2.8887222222222246,
            2.9956944444444464,
            2.9777777777777796,
            2.8083585858585884,
            2.6780808080808107,
            2.5703585858585885,
            2.706742293971464,
            2.8158559303351,
            2.867244819223989,
            2.8741337081128773,
            3.0619166666666686,
            3.0484166666666686,
            3.1525833333333355,
            3.340638888888891,
            3.3992103174603203,
            3.415626984126987,
            3.4255007215007245,
            3.282647186147189,
            3.2240757575757613,
            3.2434090909090942,
            3.313122895622899,
            3.398353324915828,
            3.5154961820586847,
            3.6549961820586847,
            3.651223033910538,
            3.661276695526699,
            3.4921338383838414,
            3.7551338383838413,
            3.908208333333336,
            3.915708333333336,
            3.924208333333336,
            3.537708333333337,
            3.2975000000000025,
            3.2704166666666694,
            3.3364166666666693,
            3.296805555555558,
            3.243055555555558,
            3.196388888888891,
            3.4163888888888914,
            3.4450000000000016,
            3.443125000000001
        ],
        "blocks": [
            {
                "Block": "99dadenggiri",
                "CurrentLevel": [
                    3.1060000000000003,
                    3.1049999999999995,
                    1.7785714285714287,
                    1.85625,
                    2.29,
                    3.1825,
                    1.912727272727273,
                    2.24,
                    2.77,
                    2.78625,
                    1.5683333333333334,
                    2.0645454545454545,
                    2.2945454545454544,
                    3.255,
                    0.7799999999999999,
                    2.225555555555556,
                    2.8966666666666665,
                    3.12625,
                    1.4144444444444444,
                    1.98625,
                    2.87125,
                    3.4044444444444446,
                    1.742222222222222,
                    2.091666666666667,
                    2.806666666666666,
                    2.03111111111111,
                    1.6688888888888893,
                    2.263,
                    2.645454545454545,
                    2.74,
                    2.1881818181818184,
                    2.5922222222222224,
                    2.628888888888889,
                    3.25375,
                    1.88,
                    2.4214285714285717,
                    3.2755555555555564,
                    1.79875,
                    1.3924999999999998,
                    1.5955555555555554,
                    2.6611111111111105,
                    2.936666666666666,
                    2.1425,
                    2.213,
                    2.5537499999999995,
                    2.793333333333333,
                    3.29,
                    2.205555555555556,
                    3.2110000000000007,
                    2.865,
                    2.6922222222222225,
                    2.786666666666667,
                    3.638888888888889,
                    2.793333333333333,
                    2.014545454545455,
                    2.265555555555556,
                    3.208,
                    3.3388681657848327,
                    2.451,
                    2.4711111111111115,
                    3.235555555555555,
                    4.09,
                    2.397,
                    2.8877777777777784,
                    3.9877777777777776,
                    4.324285714285715,
                    2.462666666666667,
                    2.927272727272728,
                    3.416363636363637,
                    4.09,
                    2.54,
                    3.206127946127946,
                    3.7572853535353534,
                    4.558571428571429,
                    3.0980000000000003,
                    3.1910353535353533,
                    3.7975,
                    3.8819999999999997,
                    4.15,
                    3.803333333333333,
                    3.8275,
                    3.916,
                    2.6039999999999996,
                    2.8425,
                    3.7191666666666654,
                    4.18,
                    2.4455555555555555,
                    2.6275,
                    3.5325,
                    5.06,
                    2.56,
                    2.62
                ],
                "AlgoLevel": [
                    NaN,
                    NaN,
                    NaN,
                    2.461455357142857,
                    2.2574553571428573,
                    2.276830357142857,
                    2.3103693181818183,
                    2.4063068181818186,
                    2.5263068181818182,
                    2.4272443181818177,
                    2.341145833333333,
                    2.2972821969696966,
                    2.1784185606060604,
                    2.295606060606061,
                    2.098522727272728,
                    2.1387752525252526,
                    2.2893055555555555,
                    2.2571180555555563,
                    2.415729166666668,
                    2.3559027777777786,
                    2.349548611111112,
                    2.419097222222223,
                    2.5010416666666675,
                    2.527395833333334,
                    2.511250000000001,
                    2.167916666666668,
                    2.149583333333334,
                    2.192416666666668,
                    2.152113636363637,
                    2.3293358585858592,
                    2.459159090909092,
                    2.5414646464646475,
                    2.5373232323232338,
                    2.6657607323232337,
                    2.5887152777777795,
                    2.546016865079366,
                    2.7076835317460333,
                    2.343933531746033,
                    2.222058531746033,
                    2.0155902777777794,
                    1.861979166666668,
                    2.1464583333333342,
                    2.3339583333333342,
                    2.4883194444444454,
                    2.461479166666668,
                    2.4256458333333346,
                    2.712520833333335,
                    2.710659722222224,
                    2.8749722222222243,
                    2.8928888888888915,
                    2.7434444444444464,
                    2.8887222222222246,
                    2.9956944444444464,
                    2.9777777777777796,
                    2.8083585858585884,
                    2.6780808080808107,
                    2.5703585858585885,
                    2.706742293971464,
                    2.8158559303351,
                    2.867244819223989,
                    2.8741337081128773,
                    3.0619166666666686,
                    3.0484166666666686,
                    3.1525833333333355,
                    3.340638888888891,
                    3.3992103174603203,
                    3.415626984126987,
                    3.4255007215007245,
                    3.282647186147189,
                    3.2240757575757613,
                    3.2434090909090942,
                    3.313122895622899,
                    3.398353324915828,
                    3.5154961820586847,
                    3.6549961820586847,
                    3.651223033910538,
                    3.661276695526699,
                    3.4921338383838414,
                    3.7551338383838413,
                    3.908208333333336,
                    3.915708333333336,
                    3.924208333333336,
                    3.537708333333337,
                    3.2975000000000025,
                    3.2704166666666694,
                    3.3364166666666693,
                    3.296805555555558,
                    3.243055555555558,
                    3.196388888888891,
                    3.4163888888888914,
                    3.4450000000000016,
                    3.443125000000001
                ]
            }
        ]
    },
    {
        "District": "West Khasi Hills",
        "IncreasingBlocks": [
            0,
            0,
            0,
            1,
            0,
            1,
            0,
            0,
            1,
            1,
            1,
            0,
            0,
            0,
            1,
            1,
            0,
            1,
            1,
            0,
            0,
            0,
            1,
            1,
            1,
            0,
            1,
            0,
            0,
            0,
            1,
            0,
            0,
            1,
            1,
            1,
            0,
            0,
            1,
            0,
            0,
            0,
            1,
            0,
            0,
            1,
            1,
            1,
            0,
            0,
            1,
            1,
            0,
            1,
            1,
            1,
            0,
            0,
            1,
            1,
            0,
            0,
            1,
            1,
            0,
            0,
            1,
            1,
            0,
            0,
            1,
            1,
            0,
            0,
            1,
            1,
            0,
            1,
            1,
            0,
            0,
            0,
            1,
            1,
            0,
            0,
            1,
            1,
            0,
            0,
            1,
            1
        ],
        "DecreasingBlocks": [
            1,
            1,
            1,
            0,
            1,
            0,
            1,
            1,
            0,
            0,
            0,
            1,
            1,
            1,
            0,
            0,
            1,
            0,
            0,
            1,
            1,
            1,
            0,
            0,
            0,
            1,
            0,
            1,
            1,
            1,
            0,
            1,
            1,
            0,
            0,
            0,
            1,
            1,
            0,
            1,
            1,
            1,
            0,
            1,
            1,
            0,
            0,
            0,
            1,
            1,
            0,
            0,
            1,
            0,
            0,
            0,
            1,
            1,
            0,
            0,
            1,
            1,
            0,
            0,
            1,
            1,
            0,
            0,
            1,
            1,
            0,
            0,
            1,
            1,
            0,
            0,
            1,
            0,
            0,
            1,
            1,
            1,
            0,
            0,
            1,
            1,
            0,
            0,
            1,
            1,
            0,
            0
        ],
        "CurrentLevel": [
            0.72,
            1.21,
            1.1,
            0.605,
            1.01,
            0.6950000000000001,
            1.23,
            1.38,
            0.625,
            0.8,
            0.55,
            0.95,
            1.56,
            2.03,
            1.0,
            1.19,
            1.42,
            0.99,
            0.77,
            1.07,
            1.22,
            1.62,
            0.5,
            1.04,
            1.05,
            0.9,
            0.86,
            1.47,
            1.41,
            1.31,
            1.18,
            1.54,
            1.85,
            0.82,
            0.6,
            1.05,
            1.07,
            1.15,
            0.9,
            1.07,
            1.05,
            1.05,
            0.78,
            1.05,
            1.16,
            0.83,
            0.72,
            0.8,
            1.3,
            0.94,
            0.55,
            0.9,
            1.65,
            0.83,
            0.47,
            0.85,
            1.3,
            1.0426470588235297,
            0.64,
            0.77,
            1.03,
            0.93,
            0.54,
            0.6,
            1.16,
            1.045,
            0.5900000000000001,
            0.7000000000000001,
            1.06,
            0.93,
            0.515,
            0.73,
            1.02,
            1.16,
            0.495,
            0.64,
            1.1166666666666667,
            0.49,
            0.49,
            0.72,
            1.27,
            0.85,
            0.5,
            0.47,
            1.27,
            0.89,
            0.47,
            0.6566666666666666,
            1.27,
            0.87,
            0.485,
            0.78
        ],
        "AlgoLevel": [
            NaN,
            NaN,
            NaN,
            0.90875,
            0.9812500000000002,
            0.8525000000000003,
            0.8850000000000001,
            1.07875,
            0.9825,
            1.0087499999999998,
            0.8387499999999998,
            0.7312499999999997,
            0.965,
            1.2724999999999995,
            1.3849999999999998,
            1.4449999999999996,
            1.4099999999999997,
            1.15,
            1.0924999999999998,
            1.0625,
            1.0125,
            1.17,
            1.1025,
            1.095,
            1.0525,
            0.8725,
            0.9625,
            1.07,
            1.16,
            1.2625000000000002,
            1.3425,
            1.36,
            1.4700000000000002,
            1.3475,
            1.2025,
            1.08,
            0.8850000000000001,
            0.9675,
            1.0425000000000002,
            1.0475000000000003,
            1.0425000000000002,
            1.0175,
            0.9875000000000002,
            0.9825000000000002,
            1.0100000000000002,
            0.9550000000000004,
            0.9400000000000002,
            0.8775000000000002,
            0.9125,
            0.94,
            0.8975,
            0.9225,
            1.01,
            0.9825,
            0.9625,
            0.95,
            0.8625000000000002,
            0.9156617647058828,
            0.9581617647058828,
            0.9381617647058824,
            0.8706617647058825,
            0.8425,
            0.8175,
            0.775,
            0.8074999999999999,
            0.8362499999999998,
            0.8487499999999999,
            0.8737499999999999,
            0.8487499999999999,
            0.8199999999999998,
            0.8012499999999998,
            0.8087499999999997,
            0.7987499999999997,
            0.8562499999999996,
            0.8512499999999996,
            0.8287499999999995,
            0.8529166666666662,
            0.6854166666666661,
            0.6841666666666661,
            0.7041666666666658,
            0.7424999999999994,
            0.8324999999999994,
            0.8349999999999993,
            0.7724999999999993,
            0.7724999999999994,
            0.7824999999999994,
            0.7749999999999995,
            0.8216666666666661,
            0.8216666666666662,
            0.8166666666666661,
            0.8204166666666661,
            0.8512499999999995
        ],
        "blocks": [
            {
                "Block": "Mawshynrut",
                "CurrentLevel": [
                    0.72,
                    1.21,
                    1.1,
                    0.605,
                    1.01,
                    0.6950000000000001,
                    1.23,
                    1.38,
                    0.625,
                    0.8,
                    0.55,
                    0.95,
                    1.56,
                    2.03,
                    1.0,
                    1.19,
                    1.42,
                    0.99,
                    0.77,
                    1.07,
                    1.22,
                    1.62,
                    0.5,
                    1.04,
                    1.05,
                    0.9,
                    0.86,
                    1.47,
                    1.41,
                    1.31,
                    1.18,
                    1.54,
                    1.85,
                    0.82,
                    0.6,
                    1.05,
                    1.07,
                    1.15,
                    0.9,
                    1.07,
                    1.05,
                    1.05,
                    0.78,
                    1.05,
                    1.16,
                    0.83,
                    0.72,
                    0.8,
                    1.3,
                    0.94,
                    0.55,
                    0.9,
                    1.65,
                    0.83,
                    0.47,
                    0.85,
                    1.3,
                    1.0426470588235297,
                    0.64,
                    0.77,
                    1.03,
                    0.93,
                    0.54,
                    0.6,
                    1.16,
                    1.045,
                    0.5900000000000001,
                    0.7000000000000001,
                    1.06,
                    0.93,
                    0.515,
                    0.73,
                    1.02,
                    1.16,
                    0.495,
                    0.64,
                    1.1166666666666667,
                    0.49,
                    0.49,
                    0.72,
                    1.27,
                    0.85,
                    0.5,
                    0.47,
                    1.27,
                    0.89,
                    0.47,
                    0.6566666666666666,
                    1.27,
                    0.87,
                    0.485,
                    0.78
                ],
                "AlgoLevel": [
                    NaN,
                    NaN,
                    NaN,
                    0.90875,
                    0.9812500000000002,
                    0.8525000000000003,
                    0.8850000000000001,
                    1.07875,
                    0.9825,
                    1.0087499999999998,
                    0.8387499999999998,
                    0.7312499999999997,
                    0.965,
                    1.2724999999999995,
                    1.3849999999999998,
                    1.4449999999999996,
                    1.4099999999999997,
                    1.15,
                    1.0924999999999998,
                    1.0625,
                    1.0125,
                    1.17,
                    1.1025,
                    1.095,
                    1.0525,
                    0.8725,
                    0.9625,
                    1.07,
                    1.16,
                    1.2625000000000002,
                    1.3425,
                    1.36,
                    1.4700000000000002,
                    1.3475,
                    1.2025,
                    1.08,
                    0.8850000000000001,
                    0.9675,
                    1.0425000000000002,
                    1.0475000000000003,
                    1.0425000000000002,
                    1.0175,
                    0.9875000000000002,
                    0.9825000000000002,
                    1.0100000000000002,
                    0.9550000000000004,
                    0.9400000000000002,
                    0.8775000000000002,
                    0.9125,
                    0.94,
                    0.8975,
                    0.9225,
                    1.01,
                    0.9825,
                    0.9625,
                    0.95,
                    0.8625000000000002,
                    0.9156617647058828,
                    0.9581617647058828,
                    0.9381617647058824,
                    0.8706617647058825,
                    0.8425,
                    0.8175,
                    0.775,
                    0.8074999999999999,
                    0.8362499999999998,
                    0.8487499999999999,
                    0.8737499999999999,
                    0.8487499999999999,
                    0.8199999999999998,
                    0.8012499999999998,
                    0.8087499999999997,
                    0.7987499999999997,
                    0.8562499999999996,
                    0.8512499999999996,
                    0.8287499999999995,
                    0.8529166666666662,
                    0.6854166666666661,
                    0.6841666666666661,
                    0.7041666666666658,
                    0.7424999999999994,
                    0.8324999999999994,
                    0.8349999999999993,
                    0.7724999999999993,
                    0.7724999999999994,
                    0.7824999999999994,
                    0.7749999999999995,
                    0.8216666666666661,
                    0.8216666666666662,
                    0.8166666666666661,
                    0.8204166666666661,
                    0.8512499999999995
                ]
            }
        ]
    },
    {
        "District": "East Garo Hills",
        "IncreasingBlocks": [
            0,
            0,
            0,
            1,
            0,
            1,
            1,
            1,
            0,
            0,
            1,
            1,
            0,
            0,
            1,
            1,
            0,
            0,
            1,
            0,
            0,
            1,
            1,
            1,
            0,
            1,
            1,
            0,
            0,
            1,
            1,
            0,
            0,
            0,
            1,
            1,
            0,
            1,
            1,
            1,
            0,
            0,
            1,
            1,
            0,
            1,
            1,
            0,
            0,
            1,
            1,
            1,
            0,
            1,
            1,
            0,
            0,
            0,
            1,
            1,
            0,
            0,
            1,
            1,
            0,
            0,
            1,
            1,
            1,
            0,
            1,
            1,
            0,
            0,
            1,
            1,
            0,
            0,
            1,
            0,
            0,
            0,
            1,
            1,
            0,
            0,
            1,
            1,
            0,
            0,
            1,
            1
        ],
        "DecreasingBlocks": [
            1,
            1,
            1,
            0,
            1,
            0,
            0,
            0,
            1,
            1,
            0,
            0,
            1,
            1,
            0,
            0,
            1,
            1,
            0,
            1,
            1,
            0,
            0,
            0,
            1,
            0,
            0,
            1,
            1,
            0,
            0,
            1,
            1,
            1,
            0,
            0,
            1,
            0,
            0,
            0,
            1,
            1,
            0,
            0,
            1,
            0,
            0,
            1,
            1,
            0,
            0,
            0,
            1,
            0,
            0,
            1,
            1,
            1,
            0,
            0,
            1,
            1,
            0,
            0,
            1,
            1,
            0,
            0,
            0,
            1,
            0,
            0,
            1,
            1,
            0,
            0,
            1,
            1,
            0,
            1,
            1,
            1,
            0,
            0,
            1,
            1,
            0,
            0,
            1,
            1,
            0,
            0
        ],
        "CurrentLevel": [
            3.481666666666667,
            1.8060000000000005,
            2.2471428571428573,
            2.3142857142857136,
            2.688333333333333,
            2.185,
            1.7716666666666665,
            2.036666666666666,
            2.683333333333333,
            2.55,
            1.5519999999999998,
            2.2425,
            2.905714285714286,
            2.7085714285714286,
            1.8666666666666665,
            2.228571428571428,
            2.6985714285714293,
            2.9199999999999995,
            2.098333333333333,
            2.6128571428571434,
            3.1039999999999996,
            2.04125,
            2.22125,
            1.7133333333333336,
            3.08,
            1.7744444444444445,
            1.5125,
            2.79375,
            2.625,
            1.6466666666666665,
            1.7777777777777777,
            2.296666666666667,
            2.894444444444445,
            2.3544444444444443,
            1.928,
            2.2125,
            3.09625,
            1.87625,
            1.7166666666666666,
            2.03,
            2.3687500000000004,
            2.1166666666666667,
            1.79375,
            2.0744444444444445,
            2.9088888888888893,
            1.6811111111111108,
            1.4866666666666668,
            2.4566666666666666,
            3.0744444444444445,
            1.8988888888888888,
            1.6411111111111107,
            1.7144444444444442,
            2.97,
            1.6811111111111108,
            1.108888888888889,
            2.45625,
            2.4111111111111105,
            2.6675152116402114,
            1.9325,
            2.0575,
            2.78125,
            3.5911111111111103,
            1.913333333333333,
            2.52125,
            3.2333333333333334,
            3.7335555555555553,
            1.8741666666666663,
            1.9744444444444444,
            2.4622222222222216,
            3.5911111111111103,
            1.7766666666666664,
            2.4485648148148145,
            3.2566666666666664,
            3.876,
            2.0162698412698408,
            2.453564814814815,
            3.1377777777777784,
            3.3922222222222214,
            1.7771428571428571,
            2.85,
            3.314285714285714,
            3.7442857142857138,
            2.495000000000001,
            2.53625,
            3.4525,
            3.97125,
            2.1385714285714283,
            2.1757142857142857,
            3.0683333333333334,
            3.78,
            2.3167857142857144,
            2.23875
        ],
        "AlgoLevel": [
            NaN,
            NaN,
            NaN,
            2.462273809523809,
            2.2639404761904762,
            2.358690476190476,
            2.239821428571428,
            2.1704166666666658,
            2.1691666666666665,
            2.2604166666666665,
            2.2055,
            2.2569583333333334,
            2.3125535714285714,
            2.3521964285714283,
            2.430863095238095,
            2.4273809523809518,
            2.3755952380952383,
            2.4284523809523813,
            2.486369047619048,
            2.5824404761904765,
            2.6837976190476187,
            2.4641101190476187,
            2.4948392857142854,
            2.2699583333333333,
            2.263958333333333,
            2.1972569444444443,
            2.0200694444444443,
            2.290173611111111,
            2.176423611111111,
            2.1444791666666663,
            2.21079861111111,
            2.086527777777777,
            2.1538888888888894,
            2.330833333333333,
            2.368388888888889,
            2.3473472222222225,
            2.397798611111111,
            2.27825,
            2.2254166666666664,
            2.179791666666666,
            1.9979166666666663,
            2.058020833333333,
            2.077291666666666,
            2.0884027777777767,
            2.2234374999999997,
            2.1145486111111103,
            2.0377777777777766,
            2.1333333333333333,
            2.174722222222222,
            2.2291666666666665,
            2.267777777777777,
            2.0822222222222218,
            2.0561111111111106,
            2.0016666666666665,
            1.8686111111111112,
            2.0540625,
            1.9143402777777772,
            2.1609413029100524,
            2.36684408068783,
            2.26715658068783,
            2.3596913029100524,
            2.5905902777777774,
            2.58579861111111,
            2.701736111111111,
            2.8147569444444445,
            2.8503680555555557,
            2.8405763888888886,
            2.703875,
            2.511097222222221,
            2.4754861111111106,
            2.4511111111111106,
            2.5696412037037035,
            2.7682523148148146,
            2.839474537037037,
            2.899375330687831,
            2.900625330687831,
            2.870903108465609,
            2.7499586640211646,
            2.6901769179894193,
            2.7892857142857146,
            2.8334126984126997,
            2.921428571428572,
            3.100892857142858,
            3.022455357142858,
            3.0570089285714293,
            3.1137500000000014,
            3.024642857142858,
            2.9345089285714296,
            2.838467261904763,
            2.790654761904763,
            2.8352083333333344,
            2.850967261904763
        ],
        "blocks": [
            {
                "Block": "Dambo Rongjeng",
                "CurrentLevel": [
                    3.481666666666667,
                    1.8060000000000005,
                    2.2471428571428573,
                    2.3142857142857136,
                    2.688333333333333,
                    2.185,
                    1.7716666666666665,
                    2.036666666666666,
                    2.683333333333333,
                    2.55,
                    1.5519999999999998,
                    2.2425,
                    2.905714285714286,
                    2.7085714285714286,
                    1.8666666666666665,
                    2.228571428571428,
                    2.6985714285714293,
                    2.9199999999999995,
                    2.098333333333333,
                    2.6128571428571434,
                    3.1039999999999996,
                    2.04125,
                    2.22125,
                    1.7133333333333336,
                    3.08,
                    1.7744444444444445,
                    1.5125,
                    2.79375,
                    2.625,
                    1.6466666666666665,
                    1.7777777777777777,
                    2.296666666666667,
                    2.894444444444445,
                    2.3544444444444443,
                    1.928,
                    2.2125,
                    3.09625,
                    1.87625,
                    1.7166666666666666,
                    2.03,
                    2.3687500000000004,
                    2.1166666666666667,
                    1.79375,
                    2.0744444444444445,
                    2.9088888888888893,
                    1.6811111111111108,
                    1.4866666666666668,
                    2.4566666666666666,
                    3.0744444444444445,
                    1.8988888888888888,
                    1.6411111111111107,
                    1.7144444444444442,
                    2.97,
                    1.6811111111111108,
                    1.108888888888889,
                    2.45625,
                    2.4111111111111105,
                    2.6675152116402114,
                    1.9325,
                    2.0575,
                    2.78125,
                    3.5911111111111103,
                    1.913333333333333,
                    2.52125,
                    3.2333333333333334,
                    3.7335555555555553,
                    1.8741666666666663,
                    1.9744444444444444,
                    2.4622222222222216,
                    3.5911111111111103,
                    1.7766666666666664,
                    2.4485648148148145,
                    3.2566666666666664,
                    3.876,
                    2.0162698412698408,
                    2.453564814814815,
                    3.1377777777777784,
                    3.3922222222222214,
                    1.7771428571428571,
                    2.85,
                    3.314285714285714,
                    3.7442857142857138,
                    2.495000000000001,
                    2.53625,
                    3.4525,
                    3.97125,
                    2.1385714285714283,
                    2.1757142857142857,
                    3.0683333333333334,
                    3.78,
                    2.3167857142857144,
                    2.23875
                ],
                "AlgoLevel": [
                    NaN,
                    NaN,
                    NaN,
                    2.462273809523809,
                    2.2639404761904762,
                    2.358690476190476,
                    2.239821428571428,
                    2.1704166666666658,
                    2.1691666666666665,
                    2.2604166666666665,
                    2.2055,
                    2.2569583333333334,
                    2.3125535714285714,
                    2.3521964285714283,
                    2.430863095238095,
                    2.4273809523809518,
                    2.3755952380952383,
                    2.4284523809523813,
                    2.486369047619048,
                    2.5824404761904765,
                    2.6837976190476187,
                    2.4641101190476187,
                    2.4948392857142854,
                    2.2699583333333333,
                    2.263958333333333,
                    2.1972569444444443,
                    2.0200694444444443,
                    2.290173611111111,
                    2.176423611111111,
                    2.1444791666666663,
                    2.21079861111111,
                    2.086527777777777,
                    2.1538888888888894,
                    2.330833333333333,
                    2.368388888888889,
                    2.3473472222222225,
                    2.397798611111111,
                    2.27825,
                    2.2254166666666664,
                    2.179791666666666,
                    1.9979166666666663,
                    2.058020833333333,
                    2.077291666666666,
                    2.0884027777777767,
                    2.2234374999999997,
                    2.1145486111111103,
                    2.0377777777777766,
                    2.1333333333333333,
                    2.174722222222222,
                    2.2291666666666665,
                    2.267777777777777,
                    2.0822222222222218,
                    2.0561111111111106,
                    2.0016666666666665,
                    1.8686111111111112,
                    2.0540625,
                    1.9143402777777772,
                    2.1609413029100524,
                    2.36684408068783,
                    2.26715658068783,
                    2.3596913029100524,
                    2.5905902777777774,
                    2.58579861111111,
                    2.701736111111111,
                    2.8147569444444445,
                    2.8503680555555557,
                    2.8405763888888886,
                    2.703875,
                    2.511097222222221,
                    2.4754861111111106,
                    2.4511111111111106,
                    2.5696412037037035,
                    2.7682523148148146,
                    2.839474537037037,
                    2.899375330687831,
                    2.900625330687831,
                    2.870903108465609,
                    2.7499586640211646,
                    2.6901769179894193,
                    2.7892857142857146,
                    2.8334126984126997,
                    2.921428571428572,
                    3.100892857142858,
                    3.022455357142858,
                    3.0570089285714293,
                    3.1137500000000014,
                    3.024642857142858,
                    2.9345089285714296,
                    2.838467261904763,
                    2.790654761904763,
                    2.8352083333333344,
                    2.850967261904763
                ]
            }
        ]
    },
    {
        "District": "Jaintia Hills",
        "IncreasingBlocks": [
            0,
            0,
            0,
            1,
            0,
            0,
            1,
            1,
            0,
            1,
            1,
            0,
            0,
            1,
            1,
            1,
            0,
            0,
            1,
            0,
            0,
            0,
            1,
            0,
            0,
            1,
            1,
            0,
            0,
            0,
            1,
            0,
            0,
            1,
            1,
            0,
            0,
            0,
            1,
            1,
            1,
            0,
            1,
            0,
            0,
            1,
            1,
            1,
            0,
            0,
            1,
            0,
            0,
            1,
            1,
            1,
            0,
            0,
            1,
            1,
            0,
            0,
            1,
            1,
            0,
            0,
            1,
            1,
            1,
            0,
            1,
            1,
            0,
            0,
            1,
            1,
            1,
            0,
            1,
            1,
            1,
            0,
            1,
            1,
            0,
            0,
            1,
            1,
            1,
            0,
            1,
            1
        ],
        "DecreasingBlocks": [
            1,
            1,
            1,
            0,
            1,
            1,
            0,
            0,
            1,
            0,
            0,
            1,
            1,
            0,
            0,
            0,
            1,
            1,
            0,
            1,
            1,
            1,
            0,
            1,
            1,
            0,
            0,
            1,
            1,
            1,
            0,
            1,
            1,
            0,
            0,
            1,
            1,
            1,
            0,
            0,
            0,
            1,
            0,
            1,
            1,
            0,
            0,
            0,
            1,
            1,
            0,
            1,
            1,
            0,
            0,
            0,
            1,
            1,
            0,
            0,
            1,
            1,
            0,
            0,
            1,
            1,
            0,
            0,
            0,
            1,
            0,
            0,
            1,
            1,
            0,
            0,
            0,
            1,
            0,
            0,
            0,
            1,
            0,
            0,
            1,
            1,
            0,
            0,
            0,
            1,
            0,
            0
        ],
        "CurrentLevel": [
            1.1,
            4.19,
            2.32,
            1.48,
            3.36,
            3.84,
            2.32,
            2.05,
            4.89,
            0.27,
            2.11,
            2.465,
            3.765,
            2.56,
            1.7375,
            2.62375,
            3.2,
            2.78,
            1.9,
            2.72,
            3.07,
            3.35,
            1.5750000000000002,
            3.26,
            3.58,
            2.7,
            1.79,
            2.74,
            3.09,
            3.405,
            1.4449999999999998,
            2.92,
            3.69,
            1.74,
            1.69,
            2.435,
            3.43,
            2.835,
            1.98,
            2.18,
            2.15,
            2.58,
            1.2,
            2.6,
            2.5,
            1.475,
            1.11,
            1.6,
            2.865,
            2.0275,
            0.9,
            2.02,
            2.51,
            1.475,
            0.755,
            1.56,
            1.475,
            2.3821875,
            1.02,
            1.08,
            2.025,
            1.6949999999999998,
            1.06,
            1.4,
            1.7,
            2.3875,
            0.9125,
            1.055,
            1.415,
            1.6949999999999998,
            0.6599999999999999,
            0.66,
            1.285,
            3.08,
            0.91,
            0.4,
            1.22625,
            2.17,
            0.5700000000000001,
            0.735,
            1.035,
            1.0699999999999998,
            0.32,
            0.77,
            1.17,
            0.935,
            0.475,
            0.31,
            0.47,
            1.0025,
            0.3975,
            0.62
        ],
        "AlgoLevel": [
            NaN,
            NaN,
            NaN,
            2.2725000000000004,
            2.8375000000000004,
            2.75,
            2.75,
            2.8925,
            3.2750000000000004,
            2.3825000000000003,
            2.33,
            2.43375,
            2.1525,
            2.725,
            2.6318750000000004,
            2.6715625000000003,
            2.5303125,
            2.5853125,
            2.6259375,
            2.65,
            2.6175,
            2.76,
            2.6787499999999995,
            2.8137499999999998,
            2.9412499999999997,
            2.7787499999999987,
            2.8325,
            2.7025,
            2.58,
            2.75625,
            2.67,
            2.715,
            2.865,
            2.44875,
            2.51,
            2.38875,
            2.32375,
            2.5975,
            2.67,
            2.60625,
            2.28625,
            2.2225,
            2.0275,
            2.1325,
            2.22,
            1.94375,
            1.9212499999999997,
            1.6712499999999997,
            1.7624999999999995,
            1.900625,
            1.848125,
            1.953125,
            1.864375,
            1.7262499999999998,
            1.6899999999999995,
            1.5749999999999995,
            1.3162499999999997,
            1.543046875,
            1.6092968749999998,
            1.489296875,
            1.626796875,
            1.455,
            1.4650000000000003,
            1.5450000000000004,
            1.4637500000000006,
            1.6368750000000007,
            1.6000000000000003,
            1.5137500000000004,
            1.4425000000000003,
            1.2693750000000004,
            1.2062500000000005,
            1.1075000000000006,
            1.0750000000000006,
            1.4212500000000006,
            1.4837500000000006,
            1.4187500000000006,
            1.4040625000000009,
            1.1765625000000006,
            1.0915625000000009,
            1.1753125000000006,
            1.1275000000000006,
            0.8525000000000005,
            0.7900000000000005,
            0.7987500000000005,
            0.8325000000000005,
            0.7987500000000006,
            0.8375000000000007,
            0.7225000000000007,
            0.5475000000000008,
            0.5643750000000007,
            0.5450000000000007,
            0.6225000000000007
        ],
        "blocks": [
            {
                "Block": "Thadlaskein",
                "CurrentLevel": [
                    1.1,
                    4.19,
                    2.32,
                    1.48,
                    3.36,
                    3.84,
                    2.32,
                    2.05,
                    4.89,
                    0.27,
                    2.11,
                    2.465,
                    3.765,
                    2.56,
                    1.7375,
                    2.62375,
                    3.2,
                    2.78,
                    1.9,
                    2.72,
                    3.07,
                    3.35,
                    1.5750000000000002,
                    3.26,
                    3.58,
                    2.7,
                    1.79,
                    2.74,
                    3.09,
                    3.405,
                    1.4449999999999998,
                    2.92,
                    3.69,
                    1.74,
                    1.69,
                    2.435,
                    3.43,
                    2.835,
                    1.98,
                    2.18,
                    2.15,
                    2.58,
                    1.2,
                    2.6,
                    2.5,
                    1.475,
                    1.11,
                    1.6,
                    2.865,
                    2.0275,
                    0.9,
                    2.02,
                    2.51,
                    1.475,
                    0.755,
                    1.56,
                    1.475,
                    2.3821875,
                    1.02,
                    1.08,
                    2.025,
                    1.6949999999999998,
                    1.06,
                    1.4,
                    1.7,
                    2.3875,
                    0.9125,
                    1.055,
                    1.415,
                    1.6949999999999998,
                    0.6599999999999999,
                    0.66,
                    1.285,
                    3.08,
                    0.91,
                    0.4,
                    1.22625,
                    2.17,
                    0.5700000000000001,
                    0.735,
                    1.035,
                    1.0699999999999998,
                    0.32,
                    0.77,
                    1.17,
                    0.935,
                    0.475,
                    0.31,
                    0.47,
                    1.0025,
                    0.3975,
                    0.62
                ],
                "AlgoLevel": [
                    NaN,
                    NaN,
                    NaN,
                    2.2725000000000004,
                    2.8375000000000004,
                    2.75,
                    2.75,
                    2.8925,
                    3.2750000000000004,
                    2.3825000000000003,
                    2.33,
                    2.43375,
                    2.1525,
                    2.725,
                    2.6318750000000004,
                    2.6715625000000003,
                    2.5303125,
                    2.5853125,
                    2.6259375,
                    2.65,
                    2.6175,
                    2.76,
                    2.6787499999999995,
                    2.8137499999999998,
                    2.9412499999999997,
                    2.7787499999999987,
                    2.8325,
                    2.7025,
                    2.58,
                    2.75625,
                    2.67,
                    2.715,
                    2.865,
                    2.44875,
                    2.51,
                    2.38875,
                    2.32375,
                    2.5975,
                    2.67,
                    2.60625,
                    2.28625,
                    2.2225,
                    2.0275,
                    2.1325,
                    2.22,
                    1.94375,
                    1.9212499999999997,
                    1.6712499999999997,
                    1.7624999999999995,
                    1.900625,
                    1.848125,
                    1.953125,
                    1.864375,
                    1.7262499999999998,
                    1.6899999999999995,
                    1.5749999999999995,
                    1.3162499999999997,
                    1.543046875,
                    1.6092968749999998,
                    1.489296875,
                    1.626796875,
                    1.455,
                    1.4650000000000003,
                    1.5450000000000004,
                    1.4637500000000006,
                    1.6368750000000007,
                    1.6000000000000003,
                    1.5137500000000004,
                    1.4425000000000003,
                    1.2693750000000004,
                    1.2062500000000005,
                    1.1075000000000006,
                    1.0750000000000006,
                    1.4212500000000006,
                    1.4837500000000006,
                    1.4187500000000006,
                    1.4040625000000009,
                    1.1765625000000006,
                    1.0915625000000009,
                    1.1753125000000006,
                    1.1275000000000006,
                    0.8525000000000005,
                    0.7900000000000005,
                    0.7987500000000005,
                    0.8325000000000005,
                    0.7987500000000006,
                    0.8375000000000007,
                    0.7225000000000007,
                    0.5475000000000008,
                    0.5643750000000007,
                    0.5450000000000007,
                    0.6225000000000007
                ]
            }
        ]
    }
]